.gitignore
.travis.yml
CHANGELOG.md
LICENSE
README.md
jetty-runner.jar
mondrian-server.properties.example
mondrian-server.war
setup.py
.scripts/README.MD
.scripts/mondrian-server.mk
docs/acl.png
docs/saiku.png
mara_mondrian/__init__.py
mara_mondrian/config.py
mara_mondrian/connection.py
mara_mondrian/schema_generation.py
mara_mondrian/views.py
mara_mondrian.egg-info/PKG-INFO
mara_mondrian.egg-info/SOURCES.txt
mara_mondrian.egg-info/dependency_links.txt
mara_mondrian.egg-info/requires.txt
mara_mondrian.egg-info/top_level.txt