Metadata-Version: 2.1
Name: mara-mondrian
Version: 2.0.2
Summary: A python integration for the Saiku ad hoc analysis tool
Home-page: https://github.com/mara/mara-mondrian
Author: Mara contributors
License: MIT
Platform: UNKNOWN
Requires-Python: >=3.6
